.installed.cfg
.mr.developer.cfg
.travis.yml
MANIFEST.in
Makefile
README.rst
base.cfg
bootstrap-py3.sh
bootstrap.py
bootstrap.sh
build_test.sh
buildout.cfg
dev.cfg
dev5.cfg
pdf.cfg
pyvenv.cfg
requirements.txt
setup.cfg
setup.py
travis.cfg.old
docs/Makefile
docs/make.bat
docs/source/HISTORY.rst
docs/source/README.rst
docs/source/conf.py
docs/source/index.rst
docs/source/_static/placeholder.txt
zopyx/__init__.py
zopyx.plone.persistentlogger.egg-info/PKG-INFO
zopyx.plone.persistentlogger.egg-info/SOURCES.txt
zopyx.plone.persistentlogger.egg-info/dependency_links.txt
zopyx.plone.persistentlogger.egg-info/entry_points.txt
zopyx.plone.persistentlogger.egg-info/namespace_packages.txt
zopyx.plone.persistentlogger.egg-info/not-zip-safe
zopyx.plone.persistentlogger.egg-info/requires.txt
zopyx.plone.persistentlogger.egg-info/top_level.txt
zopyx/plone/__init__.py
zopyx/plone/persistentlogger/__init__.py
zopyx/plone/persistentlogger/configure.zcml
zopyx/plone/persistentlogger/file_logger.py
zopyx/plone/persistentlogger/header.txt
zopyx/plone/persistentlogger/interfaces.py
zopyx/plone/persistentlogger/logger.py
zopyx/plone/persistentlogger/browser/__init__.py
zopyx/plone/persistentlogger/browser/configure.zcml
zopyx/plone/persistentlogger/browser/logger.pt
zopyx/plone/persistentlogger/browser/logger.py
zopyx/plone/persistentlogger/browser/resources/local.js
zopyx/plone/persistentlogger/browser/resources/styles.css
zopyx/plone/persistentlogger/browser/resources/DataTables/datatables.css
zopyx/plone/persistentlogger/browser/resources/DataTables/datatables.js
zopyx/plone/persistentlogger/browser/resources/DataTables/datatables.min.css
zopyx/plone/persistentlogger/browser/resources/DataTables/datatables.min.js
zopyx/plone/persistentlogger/profiles/default/actions.xml
zopyx/plone/persistentlogger/profiles/default/browserlayer.xml
zopyx/plone/persistentlogger/profiles/default/metadata.xml
zopyx/plone/persistentlogger/profiles/demo/browserlayer.xml
zopyx/plone/persistentlogger/profiles/demo/metadata.xml
zopyx/plone/persistentlogger/profiles/uninstall/readme.txt
zopyx/plone/persistentlogger/tests/__init__.py
zopyx/plone/persistentlogger/tests/base.py
zopyx/plone/persistentlogger/tests/test_logger.py