Metadata-Version: 2.1
Name: zopyx.plone.persistentlogger
Version: 0.5.2
Summary: Persistent logging for Plone objects
Home-page: http://pypi.python.org/pypi/zopyx.plone.persistentlogger
Author: Andreas Jung
Author-email: info@zopyx.com
License: GPL
Keywords: Plone Logging
Classifier: Programming Language :: Python
Classifier: Programming Language :: Python :: 3.7
Classifier: Programming Language :: Python :: 3.8
Classifier: Programming Language :: Python :: 3.9
Classifier: Programming Language :: Python :: 3.10
Classifier: Programming Language :: Python :: 3.11
Classifier: Framework :: Plone
Classifier: Framework :: Plone :: 5.2
Classifier: Framework :: Plone :: 6.0
Classifier: Framework :: Zope2
Classifier: Topic :: Software Development :: Libraries :: Python Modules
